{
  "root": false,
  "$schema": "https://biomejs.dev/schemas/2.0.4/schema.json",
  "extends": ["../../../biome.json"],
  "linter": {
    "enabled": true,
    "rules": {
      "suspicious": {
        "noExportsInTest": "off"
      },
      "style": {
        "noParameterAssign": "error",
        "useAsConstAssertion": "error",
        "useDefaultParameterLast": "warn",
        "useEnumInitializers": "error",
        "useSelfClosingElements": "error",
        "useSingleVarDeclarator": "error",
        "noUnusedTemplateLiteral": "error",
        "useNumberNamespace": "error",
        "noInferrableTypes": "error",
        "noUselessElse": "error"
      }
    }
  }
}
